conceptmap_component/__init__.py
conceptmap_component/app.py
conceptmap_component/frontend/build/bootstrap.min.css
conceptmap_component/frontend/build/index.html
conceptmap_component/frontend/build/assets/index-edbhamqC.js
st_conceptmap_cs-1.0.2.1.dist-info/licenses/LICENSE
st_conceptmap_cs-1.0.2.1.dist-info/METADATA
st_conceptmap_cs-1.0.2.1.dist-info/WHEEL
st_conceptmap_cs-1.0.2.1.dist-info/top_level.txt
st_conceptmap_cs-1.0.2.1.dist-info/RECORD
